{
 "kpis": {
  "kab_code": 3673,
  "kab_name": "Kota Serang",
  "prov_code": 36,
  "prov_name": "Banten",
  "centroid_lat": -6.1233,
  "centroid_lon": 106.1668,
  "total_events": 28,
  "total_deaths": 6,
  "total_missing": 1,
  "total_injured": 0,
  "total_houses": 8368,
  "fsi": 0.1282,
  "fsi_index": 43.27,
  "fsi_tier": "Moderate",
  "gi_cat_fsi": "Hot 90%",
  "gi_z_fsi": 1.679,
  "gi_hot_significant": true,
  "is_catastrophic": false,
  "mk_sig_event_count": false,
  "mk_sig_HCI": false,
  "mk_sig_PDI": false
 },
 "annual": {
  "years": [
   2016,
   2017,
   2018,
   2019,
   2020,
   2021,
   2022,
   2023,
   2024,
   2025
  ],
  "events": [
   0,
   0,
   0,
   0,
   2,
   6,
   4,
   2,
   9,
   5
  ],
  "deaths": [
   0,
   0,
   0,
   0,
   0,
   1,
   5,
   0,
   0,
   0
  ],
  "houses_flooded": [
   0,
   0,
   0,
   0,
   154,
   687,
   5217,
   757,
   339,
   1196
  ],
  "fsi_index": [
   0.0,
   0.0,
   0.0,
   0.0,
   9.71,
   19.36,
   29.51,
   11.1,
   16.22,
   14.85
  ],
  "hci": [
   0.0,
   0.0,
   0.0,
   0.0,
   0.0,
   0.693,
   2.485,
   0.0,
   0.0,
   0.0
  ],
  "pdi": [
   0.0,
   0.0,
   0.0,
   0.0,
   5.043,
   7.632,
   11.393,
   6.631,
   5.829,
   7.088
  ]
 },
 "monthly_heatmap": {
  "years": [
   2016,
   2017,
   2018,
   2019,
   2020,
   2021,
   2022,
   2023,
   2024,
   2025
  ],
  "months": [
   1,
   2,
   3,
   4,
   5,
   6,
   7,
   8,
   9,
   10,
   11,
   12
  ],
  "values": [
   [
    0.0,
    0.0,
    0.0,
    0.0,
    0.0,
    0.0,
    0.0,
    0.0,
    0.0,
    0.0,
    0.0,
    0.0
   ],
   [
    0.0,
    0.0,
    0.0,
    0.0,
    0.0,
    0.0,
    0.0,
    0.0,
    0.0,
    0.0,
    0.0,
    0.0
   ],
   [
    0.0,
    0.0,
    0.0,
    0.0,
    0.0,
    0.0,
    0.0,
    0.0,
    0.0,
    0.0,
    0.0,
    0.0
   ],
   [
    0.0,
    0.0,
    0.0,
    0.0,
    0.0,
    0.0,
    0.0,
    0.0,
    0.0,
    0.0,
    0.0,
    0.0
   ],
   [
    0.0,
    0.0,
    5.36,
    0.0,
    0.0,
    0.0,
    0.0,
    0.0,
    0.0,
    0.0,
    0.0,
    7.7
   ],
   [
    0.0,
    10.62,
    6.55,
    0.0,
    0.0,
    0.0,
    0.0,
    0.0,
    12.22,
    0.0,
    5.52,
    3.35
   ],
   [
    0.0,
    0.0,
    24.95,
    7.71,
    5.05,
    0.0,
    0.0,
    0.0,
    0.0,
    0.0,
    6.63,
    0.0
   ],
   [
    0.0,
    6.05,
    9.11,
    0.0,
    0.0,
    0.0,
    0.0,
    0.0,
    0.0,
    0.0,
    0.0,
    0.0
   ],
   [
    7.41,
    7.63,
    5.32,
    3.35,
    6.09,
    0.0,
    0.0,
    0.0,
    0.0,
    0.0,
    0.0,
    9.82
   ],
   [
    10.71,
    10.99,
    0.0,
    0.0,
    0.0,
    0.0,
    0.0,
    0.0,
    0.0,
    6.69,
    0.0,
    0.0
   ]
  ]
 },
 "avg_monthly": [
  1.81,
  3.53,
  5.13,
  1.11,
  1.11,
  0.0,
  0.0,
  0.0,
  1.22,
  0.67,
  1.22,
  2.09
 ]
}