{
 "kpis": {
  "kab_code": 5311,
  "kab_name": "Kabupaten Sumba Timur",
  "prov_code": 53,
  "prov_name": "Nusa Tenggara Timur",
  "centroid_lat": -9.8782,
  "centroid_lon": 120.2553,
  "total_events": 18,
  "total_deaths": 7,
  "total_missing": 0,
  "total_injured": 1,
  "total_houses": 5309,
  "fsi": 0.549,
  "fsi_percent": 52.11,
  "fsi_tier": "High",
  "gi_cat_fsi": "Cold 90%",
  "gi_z_fsi": -1.802,
  "gi_hot_significant": false,
  "is_catastrophic": false,
  "mk_sig_event_count": false,
  "mk_sig_HCI": false,
  "mk_sig_PDI": false
 },
 "annual": {
  "years": [
   2016,
   2017,
   2018,
   2019,
   2020,
   2021,
   2022,
   2023,
   2024,
   2025
  ],
  "events": [
   0,
   0,
   5,
   0,
   1,
   4,
   2,
   1,
   1,
   4
  ],
  "deaths": [
   0,
   0,
   5,
   0,
   0,
   1,
   0,
   0,
   1,
   0
  ],
  "houses_flooded": [
   0,
   0,
   192,
   0,
   44,
   2228,
   111,
   103,
   0,
   30
  ],
  "fsi_percent": [
   0.0,
   0.0,
   30.32,
   0.0,
   7.63,
   29.32,
   9.43,
   8.01,
   6.64,
   10.78
  ],
  "hci": [
   0.0,
   0.0,
   2.485,
   0.0,
   0.0,
   0.693,
   0.0,
   0.0,
   0.693,
   0.0
  ],
  "pdi": [
   0.0,
   0.0,
   11.315,
   0.0,
   4.905,
   20.912,
   4.718,
   5.338,
   0.0,
   3.434
  ]
 },
 "monthly_heatmap": {
  "years": [
   2016,
   2017,
   2018,
   2019,
   2020,
   2021,
   2022,
   2023,
   2024,
   2025
  ],
  "months": [
   1,
   2,
   3,
   4,
   5,
   6,
   7,
   8,
   9,
   10,
   11,
   12
  ],
  "values": [
   [
    0.0,
    0.0,
    0.0,
    0.0,
    0.0,
    0.0,
    0.0,
    0.0,
    0.0,
    0.0,
    0.0,
    0.0
   ],
   [
    0.0,
    0.0,
    0.0,
    0.0,
    0.0,
    0.0,
    0.0,
    0.0,
    0.0,
    0.0,
    0.0,
    0.0
   ],
   [
    4.96,
    21.28,
    10.15,
    0.0,
    0.0,
    0.0,
    0.0,
    0.0,
    0.0,
    0.0,
    0.0,
    0.0
   ],
   [
    0.0,
    0.0,
    0.0,
    0.0,
    0.0,
    0.0,
    0.0,
    0.0,
    0.0,
    0.0,
    0.0,
    0.0
   ],
   [
    0.0,
    0.0,
    0.0,
    0.0,
    5.92,
    0.0,
    0.0,
    0.0,
    0.0,
    0.0,
    0.0,
    0.0
   ],
   [
    10.23,
    4.92,
    0.0,
    16.09,
    0.0,
    0.0,
    0.0,
    0.0,
    0.0,
    0.0,
    0.0,
    0.0
   ],
   [
    0.0,
    0.0,
    0.0,
    0.0,
    0.0,
    5.4,
    0.0,
    0.0,
    0.0,
    5.32,
    0.0,
    0.0
   ],
   [
    6.19,
    0.0,
    0.0,
    0.0,
    0.0,
    0.0,
    0.0,
    0.0,
    0.0,
    0.0,
    0.0,
    0.0
   ],
   [
    0.0,
    0.0,
    6.47,
    0.0,
    0.0,
    0.0,
    0.0,
    0.0,
    0.0,
    0.0,
    0.0,
    0.0
   ],
   [
    2.79,
    2.79,
    0.0,
    0.0,
    2.79,
    0.0,
    0.0,
    0.0,
    0.0,
    0.0,
    0.0,
    4.98
   ]
  ]
 },
 "avg_monthly": [
  2.42,
  2.9,
  1.66,
  1.61,
  0.87,
  0.54,
  0.0,
  0.0,
  0.0,
  0.53,
  0.0,
  0.5
 ]
}